Siamese_Checking_Model/__init__.py
Siamese_Checking_Model/models/shape_predictor_68_face_landmarks.dat
Siamese_Checking_Model-0.0.2.dist-info/AUTHORS.rst
Siamese_Checking_Model-0.0.2.dist-info/LICENSE
Siamese_Checking_Model-0.0.2.dist-info/METADATA
Siamese_Checking_Model-0.0.2.dist-info/WHEEL
Siamese_Checking_Model-0.0.2.dist-info/top_level.txt
Siamese_Checking_Model-0.0.2.dist-info/RECORD
