Metadata-Version: 2.1
Name: Siamese-Checking-Model
Version: 0.0.2
Summary: Models used for face_recognition by siamese neural network.
Home-page: https://github.com/xalphonseinbaraj/Siamese_Checking_Model
Author: AlphonseInbarajXavier
Author-email: xalphonse@gmail.com
License: MIT license
Keywords: Siamese_Checking_Model
Platform: UNKNOWN
Classifier: Development Status :: 2 - Pre-Alpha
Classifier: Intended Audience :: Developers
Classifier: Natural Language :: English
Classifier: Programming Language :: Python :: 3.6
